pylightnix/__init__.py
pylightnix/arch.py
pylightnix/bashlike.py
pylightnix/build.py
pylightnix/core.py
pylightnix/either.py
pylightnix/garb.py
pylightnix/imports.py
pylightnix/lens.py
pylightnix/py.typed
pylightnix/repl.py
pylightnix/types.py
pylightnix/tz.py
pylightnix/utils.py
pylightnix/version.py
pylightnix/stages/__init__.py
pylightnix/stages/fetch.py
pylightnix/stages/fetch2.py
pylightnix/stages/trivial.py
pylightnix-0.3.0.dist-info/LICENSE
pylightnix-0.3.0.dist-info/METADATA
pylightnix-0.3.0.dist-info/WHEEL
pylightnix-0.3.0.dist-info/top_level.txt
pylightnix-0.3.0.dist-info/RECORD
