Metadata-Version: 2.1
Name: pylightnix
Version: 0.3.0
Summary: A Nix-style immutable data management library in Python
Home-page: https://github.com/stagedml/pylightnix
Author: grwlf
Author-email: grrwlf@gmail.com
License: UNKNOWN
Platform: UNKNOWN
Classifier: Programming Language :: Python :: 3
Classifier: License :: OSI Approved :: Apache Software License
Classifier: Operating System :: POSIX :: Linux
Classifier: Topic :: System :: Software Distribution
Classifier: Topic :: Software Development :: Build Tools
Classifier: Intended Audience :: Developers
Classifier: Development Status :: 3 - Alpha
Requires-Python: >=3.6
